safe_esg_pai_assistance_kit/__init__.py
safe_esg_pai_assistance_kit/functions.py
safe_esg_pai_assistance_kit-0.1.3.dist-info/METADATA
safe_esg_pai_assistance_kit-0.1.3.dist-info/WHEEL
safe_esg_pai_assistance_kit-0.1.3.dist-info/top_level.txt
safe_esg_pai_assistance_kit-0.1.3.dist-info/RECORD
