Metadata-Version: 2.4
Name: safe-esg-pai-assistance-kit
Version: 0.1.3
Summary: Minimal tools for SFDR PAI interpolation & diagnostics
Requires-Python: >=3.9
Requires-Dist: numpy>=1.24
Requires-Dist: pandas>=2.0
Requires-Dist: scikit-learn>=1.2
Requires-Dist: statsmodels>=0.14
Requires-Dist: matplotlib>=3.7
